[
    {
        "id": 0,
        "start_time": "2025-09-14 15:00",
        "team1": "سيلتا فيغو",
        "team2": "جيرونا",
        "logo1": "https:\/\/yallalive.sx\/wp-content\/uploads\/2021\/05\/فريق-سيلتا-فيغو.png",
        "logo1img": "فريق-سيلتا-فيغو.png",
        "logo2": "https:\/\/yallalive.sx\/wp-content\/uploads\/2022\/08\/جيرونا.png",
        "logo2img": "جيرونا.png",
        "result1": "-",
        "result2": "-",
        "event_time": "03:00 PM",
        "timer": "لم تبدأ",
        "commentator": "عبدالله الغامدي",
        "channel": "BeIN Sports 3",
        "ref": 3985737264,
        "match": 609215339,
        "league": "الدوري الاسباني",
        "urlMatch": "https:\/\/wipteetolu.net\/4\/6251800",
        "streamUrl": "XPOLA808SzJ4ZGRgYyo\/P31xZHN4PWR\/dHFpPml\/fyc+c399P3giPWBxd3U\/L3l0LSBsYHxxaXViPWRpYHUtZ3VyYHxxaXViMk0="
    },
    {
        "id": 1,
        "start_time": "2025-09-14 16:00",
        "team1": "بيرنلي",
        "team2": "ليفربول",
        "logo1": "https:\/\/yallalive.sx\/wp-content\/uploads\/2021\/05\/فريق-بيرنلي.png",
        "logo1img": "فريق-بيرنلي.png",
        "logo2": "https:\/\/yallalive.sx\/wp-content\/uploads\/2021\/04\/شعار-ليفربول.png",
        "logo2img": "شعار-ليفربول.png",
        "result1": "-",
        "result2": "-",
        "event_time": "04:00 PM",
        "timer": "لم تبدأ",
        "commentator": "علي محمد علي",
        "channel": "BeIN Sports 1",
        "ref": 2421016376,
        "match": 3997581953,
        "league": "الدوري الإنجليزي",
        "urlMatch": "https:\/\/wipteetolu.net\/4\/6251800",
        "streamUrl": "XPOLA808SzJ4ZGRgYyo\/P31xZHN4PWR\/dHFpPml\/fyc+c399P3giPWBxd3U\/L3l0LSFsYHxxaXViPWRpYHUtZ3VyYHxxaXViMk0="
    },
    {
        "id": 2,
        "start_time": "2025-09-14 16:00",
        "team1": "نادي ليل",
        "team2": "تولوز",
        "logo1": "https:\/\/yallalive.sx\/wp-content\/uploads\/2021\/05\/نادي-ليل.png",
        "logo1img": "نادي-ليل.png",
        "logo2": "https:\/\/yallalive.sx\/wp-content\/uploads\/2022\/08\/تولوز.png",
        "logo2img": "تولوز.png",
        "result1": "-",
        "result2": "-",
        "event_time": "04:00 PM",
        "timer": "لم تبدأ",
        "commentator": "باسم الزير",
        "channel": "BeIN Sports 4",
        "ref": 3201827960,
        "match": 48807456,
        "league": "الدوري الفرنسي",
        "urlMatch": "https:\/\/wipteetolu.net\/4\/6251800",
        "streamUrl": "XPOLA808SzJ4ZGRgYyo\/P31xZHN4PWR\/dHFpPml\/fyc+c399P3giPWBxd3U\/L3l0LSJsYHxxaXViPWRpYHUtZ3VyYHxxaXViMk0="
    },
    {
        "id": 3,
        "start_time": "2025-09-14 18:15",
        "team1": "باريس سان جيرمان",
        "team2": "لانس",
        "logo1": "https:\/\/yallalive.sx\/wp-content\/uploads\/2021\/04\/فريق-باريس-سان-جيرمان.png",
        "logo1img": "فريق-باريس-سان-جيرمان.png",
        "logo2": "https:\/\/yallalive.sx\/wp-content\/uploads\/2021\/05\/لانس.png",
        "logo2img": "لانس.png",
        "result1": "-",
        "result2": "-",
        "event_time": "06:15 PM",
        "timer": "لم تبدأ",
        "commentator": "احمد البلوشي",
        "channel": "BeIN Sports 2",
        "ref": 615502624,
        "match": 650096065,
        "league": "الدوري الفرنسي",
        "urlMatch": "https:\/\/wipteetolu.net\/4\/6251800",
        "streamUrl": "XPOLA808SzJ4ZGRgYyo\/P31xZHN4PWR\/dHFpPml\/fyc+c399P3giPWBxd3U\/L3l0LSNsYHxxaXViPWRpYHUtZ3VyYHxxaXViMk0="
    },
    {
        "id": 4,
        "start_time": "2025-09-14 18:30",
        "team1": "مان سيتي",
        "team2": "مان يونايتد",
        "logo1": "https:\/\/yallalive.sx\/wp-content\/uploads\/2021\/04\/شعار-مان-سيتي.png",
        "logo1img": "شعار-مان-سيتي.png",
        "logo2": "https:\/\/yallalive.sx\/wp-content\/uploads\/2021\/04\/شعار-مان-يونايتد.png",
        "logo2img": "شعار-مان-يونايتد.png",
        "result1": "-",
        "result2": "-",
        "event_time": "06:30 PM",
        "timer": "لم تبدأ",
        "commentator": "عصام الشوالي",
        "channel": "BeIN Sports 1",
        "ref": 2421016376,
        "match": 2366911366,
        "league": "الدوري الإنجليزي",
        "urlMatch": "https:\/\/wipteetolu.net\/4\/6251800",
        "streamUrl": "XPOLA808SzJ4ZGRgYyo\/P2d\/PnN9cT52f39kcnF8fHl5PnliP3h8YyI\/ciE+fSNlKGx+cX11LVlCMjwyeGRkYGMqPz90ez5nfz52f39kcnF8fHl5PnliP3h8YyI\/ciE+fSNlKGx+cX11LVlCMjwyeGRkYGMqPz9zdH52dWNkPnN\/fT9zeCAhP2Z5dHV\/Pn0jZShsfnF9dS1WVTI8MnhkZGBjKj8\/cSE+cWB7PXFgeT5zf30\/cWB5P3N4cX5+dXw\/ISQiJGx+cX11LUlRMjwyeGRkYGMqPz9xIT5xYHs9cWB5PnN\/fT9xYHk\/c3hxfn51fD8kJGx+cX11LUlRMjwyeGRkYGMqPz90f3t7fyF+dWc+fnVne2N\/PmJlP3R\/e3t\/IT9gYnV9eWV9KSE\/fX9+fz59I2UobHFlZHgteGRkYGMqPz96aH9oe2B8cWk+aGlqP2N1YmZ1Yk98f397ZWA+YHhgL3N4cX5+dXxPeXQtYGJ1fXllfWxlY3ViPXF3dX5kLV1\/anl8fHE\/JT4gMDhIISErMFx5fmVoMGgoJk8mJDkwUWBgfHVHdXJbeWQ\/JSMkPiIkMDhbWERdXDwwfHl7dTBXdXN7fzkwU3hif311PyEhPiA+JikmPiMkMENxdnFieT8lIyQ+IiRsYnV2dWJ1Yi14ZGRgYyo\/P3pof2h7YHxxaT5oaWo\/bH5xfXUtQEJVMk0="
    }
]