[
    {
        "id": 0,
        "start_time": "2025-12-28 14:30",
        "team1": "ميلان",
        "team2": "هيلاس فيرونا",
        "logo1": "https:\/\/yallalive.sx\/wp-content\/uploads\/2021\/04\/ميلان.png",
        "logo1img": "ميلان.png",
        "logo2": "https:\/\/yallalive.sx\/wp-content\/uploads\/2021\/04\/هيلاس-فيرونا.png",
        "logo2img": "هيلاس-فيرونا.png",
        "result1": "-",
        "result2": "-",
        "event_time": "02:30 PM",
        "timer": "لم تبدأ",
        "commentator": "علي دراج",
        "channel": "شاشا",
        "ref": 1173260895,
        "match": 2548639201,
        "league": "الدوري الايطالي",
        "urlMatch": "https:\/\/wipteetolu.net\/4\/6251800",
        "streamUrl": "XPOLA808SzJ4ZGRgYyo\/P3d5ZHhlcj5zf30\/Znl0dX89aGB8cWl1Yj9meXR1f2M\/YnFnP2J1dmM\/eHVxdGM\/fXF5fj92cXxjdT59YCQyTQ=="
    },
    {
        "id": 1,
        "start_time": "2025-12-28 15:30",
        "team1": "الجابون",
        "team2": "موزمبيق",
        "logo1": "https:\/\/yallalive.sx\/wp-content\/uploads\/2021\/09\/الغابون.png",
        "logo1img": "الغابون.png",
        "logo2": "https:\/\/yallalive.sx\/wp-content\/uploads\/2024\/01\/ID0I1bCWjgAqS9iWqw-08A_96x961.png",
        "logo2img": "ID0I1bCWjgAqS9iWqw-08A_96x961.png",
        "result1": "-",
        "result2": "-",
        "event_time": "03:30 PM",
        "timer": "لم تبدأ",
        "commentator": "جواد بدهـ",
        "channel": "BeIN MAX1",
        "ref": 3127654706,
        "match": 3021511246,
        "league": "كأس أمم إفريقيا",
        "urlMatch": "https:\/\/wipteetolu.net\/4\/6251800",
        "streamUrl": "XPOLA808SzJ4ZGRgYyo\/P3EiPnFgez1xYHk+c399P3FgeT9zeHF+fnV8PyElIiFsfnF9dS1DITI8MnhkZGBjKj8\/cSI+cWB7PXFgeT5zf30\/cWB5P3N4cX5+dXw\/ISUiImx+cX11LUMiMjwyeGRkYGMqPz9xIj5xYHs9cWB5PnN\/fT9xYHk\/c3hxfn51fD8hJCIiMk0="
    },
    {
        "id": 2,
        "start_time": "2025-12-28 17:00",
        "team1": "كريمونيزي",
        "team2": "نابولي",
        "logo1": "https:\/\/yallalive.sx\/wp-content\/uploads\/2022\/08\/كريمونيزي.png",
        "logo1img": "كريمونيزي.png",
        "logo2": "https:\/\/yallalive.sx\/wp-content\/uploads\/2021\/04\/شعار-نابولي.png",
        "logo2img": "شعار-نابولي.png",
        "result1": "-",
        "result2": "-",
        "event_time": "05:00 PM",
        "timer": "لم تبدأ",
        "commentator": "هاني الشهري",
        "channel": "شاشا",
        "ref": 1173260895,
        "match": 1346112461,
        "league": "الدوري الايطالي",
        "urlMatch": "https:\/\/wipteetolu.net\/4\/6251800",
        "streamUrl": "XPOLA808SzJ4ZGRgYyo\/P3d5ZHhlcj5zf30\/Znl0dX89aGB8cWl1Yj9meXR1f2M\/YnFnP2J1dmM\/eHVxdGM\/fXF5fj92cXxjdT59YCQyTQ=="
    },
    {
        "id": 3,
        "start_time": "2025-12-28 17:00",
        "team1": "سندرلاند",
        "team2": "ليدز يونايتد",
        "logo1": "https:\/\/yallalive.sx\/wp-content\/uploads\/2021\/12\/سندرلاند.png",
        "logo1img": "سندرلاند.png",
        "logo2": "https:\/\/yallalive.sx\/wp-content\/uploads\/2021\/04\/ليدز-يونايتد.png",
        "logo2img": "ليدز-يونايتد.png",
        "result1": "-",
        "result2": "-",
        "event_time": "05:00 PM",
        "timer": "لم تبدأ",
        "commentator": "محمد بركات",
        "channel": "BeIN Sports 1",
        "ref": 2421016376,
        "match": 3524924641,
        "league": "الدوري الإنجليزي",
        "urlMatch": "https:\/\/wipteetolu.net\/4\/6251800",
        "streamUrl": "XPOLA808SzJ4ZGRgYyo\/P3EhPnFgez1xYHk+c399P3FgeT9zeHF+fnV8PyEkIiRsfnF9dS1JUTI8MnhkZGBjKj8\/cSE+cWB7PXFgeT5zf30\/cWB5P3N4cX5+dXw\/JCRsfnF9dS1JUTI8MnhkZGAqPz8hJyY+ISEpPiIpPic\/IHMlJSUnI3Q9ISJ0KD0kI3F2PSgiI3I9IiVzKSR0JidyISkgPn0jZShsfnF9dS0hJzI8MnhkZGBjKj8\/YXF+cWQlPmN5ZHU\/ZWB8f3F0P3l9cXd1Yz98f3d\/IT5qeWBsZWN1Yj1xd3V+ZC1df2p5fHxxPyU+IDA4eUB4f351KzBTQEUweUB4f351MF9DMCEmTyYwfHl7dTBdcXMwX0MwSDkwUWBgfHVHdXJbeWQ\/JiAlPiE+ISUwOFtYRF1cPDB8eXt1MFd1c3t\/OTBGdWJjeX9+PyEmPiYwXX9yeXx1PyElVSEkKDBDcXZxYnk\/JiAkPiFsYnV2dWJ1Yi14ZGRgYyo\/P2dnZz5pcWJ5d3E+fHlmdT9sfnF9dS1JUUIyTQ=="
    },
    {
        "id": 4,
        "start_time": "2025-12-28 18:00",
        "team1": "غينيا الإستوائية",
        "team2": "السودان",
        "logo1": "https:\/\/yallalive.sx\/wp-content\/uploads\/2021\/11\/غينيا-الإستوائية.png",
        "logo1img": "غينيا-الإستوائية.png",
        "logo2": "https:\/\/yallalive.sx\/wp-content\/uploads\/2021\/06\/السودان.png",
        "logo2img": "السودان.png",
        "result1": "-",
        "result2": "-",
        "event_time": "06:00 PM",
        "timer": "لم تبدأ",
        "commentator": "علي محمد علي",
        "channel": "BeIN MAX1",
        "ref": 3127654706,
        "match": 3897360838,
        "league": "كأس أمم أفريقيا",
        "urlMatch": "https:\/\/wipteetolu.net\/4\/6251800",
        "streamUrl": "XPOLA808SzJ4ZGRgYyo\/P3EiPnFgez1xYHk+c399P3FgeT9zeHF+fnV8PyElIiFsfnF9dS1DITI8MnhkZGBjKj8\/cSI+cWB7PXFgeT5zf30\/cWB5P3N4cX5+dXw\/ISUiImx+cX11LUMiMjwyeGRkYGMqPz9xIj5xYHs9cWB5PnN\/fT9xYHk\/c3hxfn51fD8hJCIiMk0="
    },
    {
        "id": 5,
        "start_time": "2025-12-28 19:30",
        "team1": "كريستال بالاس",
        "team2": "توتنهام",
        "logo1": "https:\/\/yallalive.sx\/wp-content\/uploads\/2021\/04\/فريق-كريستال-بالاس.png",
        "logo1img": "فريق-كريستال-بالاس.png",
        "logo2": "https:\/\/yallalive.sx\/wp-content\/uploads\/2021\/04\/توتنهام.png",
        "logo2img": "توتنهام.png",
        "result1": "-",
        "result2": "-",
        "event_time": "07:30 PM",
        "timer": "لم تبدأ",
        "commentator": "حسن العيدروس",
        "channel": "BeIN Sports 1",
        "ref": 2421016376,
        "match": 3923379819,
        "league": "الدوري الإنجليزي",
        "urlMatch": "https:\/\/wipteetolu.net\/4\/6251800",
        "streamUrl": "XPOLA808SzJ4ZGRgYyo\/P3EhPnFgez1xYHk+c399P3FgeT9zeHF+fnV8PyEkIiRsfnF9dS1JUTI8MnhkZGBjKj8\/cSE+cWB7PXFgeT5zf30\/cWB5P3N4cX5+dXw\/JCRsfnF9dS1JUTI8MnhkZGAqPz8hJyY+ISEpPiIpPic\/IHMlJSUnI3Q9ISJ0KD0kI3F2PSgiI3I9IiVzKSR0JidyISkgPn0jZShsfnF9dS0hJzI8MnhkZGBjKj8\/YXF+cWQlPmN5ZHU\/ZWB8f3F0P3l9cXd1Yz98f3d\/IT5qeWBsZWN1Yj1xd3V+ZC1df2p5fHxxPyU+IDA4eUB4f351KzBTQEUweUB4f351MF9DMCEmTyYwfHl7dTBdcXMwX0MwSDkwUWBgfHVHdXJbeWQ\/JiAlPiE+ISUwOFtYRF1cPDB8eXt1MFd1c3t\/OTBGdWJjeX9+PyEmPiYwXX9yeXx1PyElVSEkKDBDcXZxYnk\/JiAkPiFsYnV2dWJ1Yi14ZGRgYyo\/P2dnZz5pcWJ5d3E+fHlmdT9sfnF9dS1JUUIyTQ=="
    },
    {
        "id": 6,
        "start_time": "2025-12-28 20:30",
        "team1": "الجزائر",
        "team2": "بوركينا فاسو",
        "logo1": "https:\/\/yallalive.sx\/wp-content\/uploads\/2021\/11\/الجزائر.png",
        "logo1img": "الجزائر.png",
        "logo2": "https:\/\/yallalive.sx\/wp-content\/uploads\/2021\/11\/بوركينا-فاسو.png",
        "logo2img": "بوركينا-فاسو.png",
        "result1": "-",
        "result2": "-",
        "event_time": "08:30 PM",
        "timer": "لم تبدأ",
        "commentator": "حفيظ الدراجي",
        "channel": "BeIN MAX1",
        "ref": 3127654706,
        "match": 644417265,
        "league": "كأس أمم أفريقيا",
        "urlMatch": "https:\/\/wipteetolu.net\/4\/6251800",
        "streamUrl": "XPOLA808SzJ4ZGRgYyo\/P3EiPnFgez1xYHk+c399P3FgeT9zeHF+fnV8PyElIiFsfnF9dS1DITI8MnhkZGBjKj8\/cSI+cWB7PXFgeT5zf30\/cWB5P3N4cX5+dXw\/ISUiImx+cX11LUMiMjwyeGRkYGMqPz9xIj5xYHs9cWB5PnN\/fT9xYHk\/c3hxfn51fD8hJCIiMk0="
    },
    {
        "id": 7,
        "start_time": "2025-12-28 22:45",
        "team1": "أتالانتا",
        "team2": "انتر ميلان",
        "logo1": "https:\/\/yallalive.sx\/wp-content\/uploads\/2021\/04\/أتلانتا.png",
        "logo1img": "أتلانتا.png",
        "logo2": "https:\/\/yallalive.sx\/wp-content\/uploads\/2021\/04\/انتر-ميلان.png",
        "logo2img": "انتر-ميلان.png",
        "result1": "-",
        "result2": "-",
        "event_time": "10:45 PM",
        "timer": "لم تبدأ",
        "commentator": "علي دراج",
        "channel": "شاشا",
        "ref": 1173260895,
        "match": 3588950743,
        "league": "الدوري الايطالي",
        "urlMatch": "https:\/\/wipteetolu.net\/4\/6251800",
        "streamUrl": "XPOLA808SzJ4ZGRgYyo\/P3d5ZHhlcj5zf30\/Znl0dX89aGB8cWl1Yj9meXR1f2M\/YnFnP2J1dmM\/eHVxdGM\/fXF5fj92cXxjdT59YCQyTQ=="
    }
]